LICENSE
LICENSE.txt
MANIFEST.in
README.rst
setup.py
tox.ini
common_feature/__init__.py
common_feature/_context_processors.py
common_feature/_import_lib.py
common_feature/_views.py
common_feature/models.py
common_feature/settings.py
common_feature/urls.py
common_feature/wsgi.py
common_feature.egg-info/PKG-INFO
common_feature.egg-info/SOURCES.txt
common_feature.egg-info/dependency_links.txt
common_feature.egg-info/requires.txt
common_feature.egg-info/top_level.txt
common_feature/database/__init__.py
common_feature/database/admin_management/__init__.py
common_feature/database/admin_management/admin.py
common_feature/database/admin_management/admin_views.py
common_feature/database/admin_management/models.py
common_feature/database/admin_management/urls.py
common_feature/database/admin_management/admin/AdminSQL.html
common_feature/database/common/__init__.py
common_feature/database/common/admin.py
common_feature/database/common/model_choices.py
common_feature/database/common/models.py
common_feature/database/common/utils.py
common_feature/database/location/__init__.py
common_feature/database/location/admin.py
common_feature/database/location/models.py
common_feature/database/physical/__init__.py
common_feature/database/physical/admin.py
common_feature/database/physical/model_choices.py
common_feature/database/physical/models.py
common_feature/database/time_n_date/__init__.py
common_feature/database/time_n_date/model_choices.py
common_feature/database/time_n_date/models.py
common_feature/database/time_n_date/utils.py
common_feature/docs/task.txt
common_feature/migrations/0001_initial.py
common_feature/migrations/__init__.py
common_feature/operation/__init__.py
common_feature/operation/calculations/__init__.py
common_feature/operation/calculations/utils.py
common_feature/operation/data/__init__.py
common_feature/operation/data/_color.py
common_feature/operation/data/_data.py
common_feature/operation/data/_data_utils.py
common_feature/operation/dict/__init__.py
common_feature/operation/dict/utils.py
common_feature/operation/email/__init__.py
common_feature/operation/email/utils.py
common_feature/operation/excel/__init__.py
